odoo/addons/purchase_sale_link_by_origin/README.rst
odoo/addons/purchase_sale_link_by_origin/__init__.py
odoo/addons/purchase_sale_link_by_origin/__manifest__.py
odoo/addons/purchase_sale_link_by_origin/i18n/it.po
odoo/addons/purchase_sale_link_by_origin/i18n/pt_BR.po
odoo/addons/purchase_sale_link_by_origin/i18n/purchase_sale_link_by_origin.pot
odoo/addons/purchase_sale_link_by_origin/i18n/sl.po
odoo/addons/purchase_sale_link_by_origin/models/__init__.py
odoo/addons/purchase_sale_link_by_origin/models/purchase_order.py
odoo/addons/purchase_sale_link_by_origin/models/sale_order.py
odoo/addons/purchase_sale_link_by_origin/readme/CONTRIBUTORS.md
odoo/addons/purchase_sale_link_by_origin/readme/CREDITS.md
odoo/addons/purchase_sale_link_by_origin/readme/DESCRIPTION.md
odoo/addons/purchase_sale_link_by_origin/static/description/icon.png
odoo/addons/purchase_sale_link_by_origin/static/description/index.html
odoo/addons/purchase_sale_link_by_origin/tests/__init__.py
odoo/addons/purchase_sale_link_by_origin/tests/test_sale_purchase.py
odoo_addon_purchase_sale_link_by_origin-18.0.1.0.0.5.dist-info/METADATA
odoo_addon_purchase_sale_link_by_origin-18.0.1.0.0.5.dist-info/WHEEL
odoo_addon_purchase_sale_link_by_origin-18.0.1.0.0.5.dist-info/top_level.txt
odoo_addon_purchase_sale_link_by_origin-18.0.1.0.0.5.dist-info/RECORD
