Metadata-Version: 2.1
Name: odoo-addon-purchase_sale_link_by_origin
Version: 18.0.1.0.0.5
Requires-Python: >=3.10
Requires-Dist: odoo==18.0.*
Summary: Link PO/SO by the PO's Origin in addition to the default behavior that only links them by their lines
Home-page: https://github.com/OCA/purchase-workflow
License: AGPL-3
Author: Camptocamp, Odoo Community Association (OCA)
Author-email: support@odoo-community.org
Classifier: Programming Language :: Python
Classifier: Framework :: Odoo
Classifier: Framework :: Odoo :: 18.0
Classifier: License :: OSI Approved :: GNU Affero General Public License v3
